{
    "resourceType": "Bundle",
    "id": "example-rec-01-true-make-recommendations",
    "type": "transaction",
    "entry": [
        {
            "fullUrl": "http://measure.eval.kanvix.com/cqf-ruler/baseDstu3/Patient/example-rec-01-true-make-recommendations",
            "resource": {
                "resourceType": "Patient",
                "id": "example-rec-01-true-make-recommendations",
                "meta": {
                    "profile": [
                        "http://hl7.org/fhir/profiles/Patient"
                    ]
                }
            },
            "birthDate": {
              "extension": [
                {
                  "url": "http://hl7.org/fhir/StructureDefinition/cqf-cqlExpression",
                  "valueString": "Today() - 20 years"
                }
              ]
            },
            "request": {
                "method": "PUT",
                "url": "Patient/example-rec-01-true-make-recommendations"
            }
        },
        {
            "fullUrl": "http://measure.eval.kanvix.com/cqf-ruler/baseDstu3/MedicationStatement/example-rec-01-true-make-recommendations",
            "resource": {
                "resourceType": "MedicationStatement",
                "meta": {
                    "profile": [
                        "http://hl7.org/fhir/profiles/MedicationStatement"
                    ]
                },
                "id": "example-rec-01-true-make-recommendations",
                "status": "active",
                "subject": {
                    "reference": "Patient/example-rec-01-true-make-recommendations"
                },
                "effectiveDateTime":
                {
                  "extension": [
                    {
                      "url": "http://hl7.org/fhir/StructureDefinition/cqf-cqlExpression",
                      "valueString": "Today() - 95 days"
                    }
                  ]
                },
                "medicationCodeableConcept": {
                    "coding": [
                        {
                            "system": "http://www.nlm.nih.gov/research/umls/rxnorm",
                            "code": "1010603",
                            "display": "Ambulatory Abuse Potential Opioids"
                        }
                    ]
                }
            },
            "request": {
                "method": "PUT",
                "url": "MedicationStatement/example-rec-01-true-make-recommendations"
            }
        },
        {
            "fullUrl": "http://measure.eval.kanvix.com/cqf-ruler/baseDstu3/MedicationRequest/example-rec-01-true-make-recommendations",
            "resource": {
                "resourceType": "MedicationRequest",
                "meta": {
                    "profile": [
                        "http://hl7.org/fhir/profiles/MedicationRequest"
                    ]
                },
                "id": "example-rec-01-true-make-recommendations",
                "status": "active",
                "intent": "order",
                "subject": {
                    "reference": "Patient/example-rec-01-true-make-recommendations"
                },
                "category": {
                    "coding": [
                        {
                            "system": "http://hl7.org/fhir/ValueSet/medication-dispense-category",
                            "code": "outpatient",
                            "display": "Outpatient"
                        }
                    ]
                },
                "medicationCodeableConcept": {
                    "coding": [
                        {
                            "system": "http://www.nlm.nih.gov/research/umls/rxnorm",
                            "code": "1010603",
                            "display": "Ambulatory Abuse Potential Opioids"
                        }
                    ]
                }
            },
            "request": {
                "method": "PUT",
                "url": "MedicationRequest/example-rec-01-true-make-recommendations"
            }
        }
    ]
}
